{
  "users": [
    {
      "id": 1,
      "name": "Juan",
      "phone": "4321",
      "password": "54321",
      "img": "esamisma",
      "flag": "npi",
      "info": "es mi hermano"
    },
    {
      "id": 2,
      "name": "Carlos",
      "phone": "1234",
      "password": "12345",
      "img": "esamisma",
      "flag": "npi",
      "info": "soy muy buen programador"
    }
  ],
  "msn": [
    {
      "idUser1": "",
      "idUser2": "",
      "conversations": [
        {
          "senBy": "",
          "date": "",
          "hour": "",
          "message": "",
          "confirm": ""
        }
      ]
    }
  ]
}
